jupytext/__init__.py
jupytext/__main__.py
jupytext/cell_metadata.py
jupytext/cell_reader.py
jupytext/cell_to_text.py
jupytext/cli.py
jupytext/combine.py
jupytext/compare.py
jupytext/config.py
jupytext/contentsmanager.py
jupytext/doxygen.py
jupytext/formats.py
jupytext/header.py
jupytext/jupytext.py
jupytext/kernels.py
jupytext/languages.py
jupytext/magics.py
jupytext/metadata_filter.py
jupytext/myst.py
jupytext/paired_paths.py
jupytext/pairs.py
jupytext/pandoc.py
jupytext/pep8.py
jupytext/reraise.py
jupytext/stringparser.py
jupytext/version.py
jupytext/nbextension/README.md
jupytext/nbextension/Untitled.py
jupytext/nbextension/index.js
jupytext/nbextension/jupytext.yml
jupytext/nbextension/jupytext_menu.png
jupytext/nbextension/jupytext_menu_zoom.png
jupytext_ebp-1.12.0a1.data/data/etc/jupyter/jupyter_notebook_config.d/jupytext.json
jupytext_ebp-1.12.0a1.data/data/etc/jupyter/jupyter_server_config.d/jupytext.json
jupytext_ebp-1.12.0a1.data/data/etc/jupyter/nbconfig/notebook.d/jupytext.json
jupytext_ebp-1.12.0a1.data/data/share/jupyter/nbextensions/jupytext/README.md
jupytext_ebp-1.12.0a1.data/data/share/jupyter/nbextensions/jupytext/index.js
jupytext_ebp-1.12.0a1.data/data/share/jupyter/nbextensions/jupytext/jupytext.yml
jupytext_ebp-1.12.0a1.data/data/share/jupyter/nbextensions/jupytext/jupytext_menu.png
jupytext_ebp-1.12.0a1.dist-info/LICENSE
jupytext_ebp-1.12.0a1.dist-info/METADATA
jupytext_ebp-1.12.0a1.dist-info/WHEEL
jupytext_ebp-1.12.0a1.dist-info/entry_points.txt
jupytext_ebp-1.12.0a1.dist-info/top_level.txt
jupytext_ebp-1.12.0a1.dist-info/RECORD
