Metadata-Version: 2.1
Name: jupytext-ebp
Version: 1.12.0a1
Summary: Jupyter notebooks as Markdown documents, Julia, Python or R scripts
Home-page: https://github.com/mwouts/jupytext
Author: Marc Wouts
Author-email: marc.wouts@gmail.com
License: MIT
Platform: UNKNOWN
Classifier: Development Status :: 5 - Production/Stable
Classifier: License :: OSI Approved :: MIT License
Classifier: Environment :: Console
Classifier: Framework :: Jupyter
Classifier: Intended Audience :: Developers
Classifier: Intended Audience :: Science/Research
Classifier: Topic :: Text Processing :: Markup
Classifier: Programming Language :: Python
Classifier: Programming Language :: Python :: 3
Classifier: Programming Language :: Python :: 3.6
Classifier: Programming Language :: Python :: 3.7
Classifier: Programming Language :: Python :: 3.8
Classifier: Programming Language :: Python :: 3.9
Requires-Python: ~=3.6
Requires-Dist: nbformat
Requires-Dist: pyyaml
Requires-Dist: toml
Requires-Dist: markdown-it-py[plugins] (<2,>=1.0.0b2)
Provides-Extra: myst
Provides-Extra: rst2md
Requires-Dist: sphinx-gallery (~=0.7.0) ; extra == 'rst2md'
Provides-Extra: toml
Requires-Dist: toml ; extra == 'toml'
